cuckoopy/__init__.py
cuckoopy/bucket.py
cuckoopy/cuckoofilter.py
cuckoopy/exceptions.py
cuckoopy/hashutils.py
cuckoopy-0.1.1.dist-info/DESCRIPTION.rst
cuckoopy-0.1.1.dist-info/METADATA
cuckoopy-0.1.1.dist-info/RECORD
cuckoopy-0.1.1.dist-info/WHEEL
cuckoopy-0.1.1.dist-info/metadata.json
cuckoopy-0.1.1.dist-info/top_level.txt
