Metadata-Version: 1.1
Name: cuckoopy
Version: 0.1.1
Summary: Cuckoo Filter implementation in Python
Home-page: https://github.com/rajathagasthya/cuckoopy
Author: Rajath Agasthya
Author-email: rajathagasthya@gmail.com
License: MIT
Platform: UNKNOWN
Classifier: Development Status :: 3 - Alpha
Classifier: Intended Audience :: Developers
Classifier: Natural Language :: English
Classifier: License :: OSI Approved :: MIT License
Classifier: Programming Language :: Python
Classifier: Programming Language :: Python :: 3
Classifier: Programming Language :: Python :: 3.5
Classifier: Programming Language :: Python :: 3.6
